airflow/providers/taskette/__init__.py
airflow/providers/taskette/exceptions.py
airflow/providers/taskette/get_provider_info.py
airflow/providers/taskette/get_provider_info_old.py
airflow/providers/taskette/version_compat.py
airflow/providers/taskette/hooks/__init__.py
airflow/providers/taskette/hooks/taskette_base.py
airflow/providers/taskette/operators/__init__.py
airflow/providers/taskette/operators/taskette.py
airflow/providers/taskette/plugins/__init__.py
airflow/providers/taskette/plugins/taskette.py
airflow/providers/taskette/sensors/__init__.py
airflow/providers/taskette/sensors/taskette.py
airflow/providers/taskette/triggers/__init__.py
airflow/providers/taskette/triggers/taskette.py
airflow/providers/taskette/utils/__init__.py
airflow/providers/taskette/utils/taskette.py
apache_airflow_providers_taskette_dev-0.0.2.dist-info/entry_points.txt
apache_airflow_providers_taskette_dev-0.0.2.dist-info/WHEEL
apache_airflow_providers_taskette_dev-0.0.2.dist-info/METADATA
apache_airflow_providers_taskette_dev-0.0.2.dist-info/RECORD
