Metadata-Version: 2.4
Name: apache-airflow-providers-taskette-dev
Version: 0.0.2
Summary: Provider package apache-airflow-providers-taskette for Apache Airflow
Keywords: airflow-provider,taskette,airflow,integration
Author-email: Forrest Bajbek <forrestbajbek@gmail.com>, Michael van Dyk <mvandyk@protonmail.com>
Maintainer-email: Forrest Bajbek <forrestbajbek@gmail.com>, Michael van Dyk <mvandyk@protonmail.com>
Requires-Python: >=3.10
Classifier: Development Status :: 5 - Production/Stable
Classifier: Environment :: Console
Classifier: Environment :: Web Environment
Classifier: Intended Audience :: Developers
Classifier: Intended Audience :: System Administrators
Classifier: Framework :: Apache Airflow
Classifier: Framework :: Apache Airflow :: Provider
Classifier: License :: OSI Approved :: Apache Software License
Classifier: Programming Language :: Python :: 3.10
Classifier: Programming Language :: Python :: 3.11
Classifier: Programming Language :: Python :: 3.12
Classifier: Programming Language :: Python :: 3.13
Classifier: Topic :: System :: Monitoring
Requires-Dist: apache-airflow>=2.10.0
Requires-Dist: apache-airflow-providers-common-compat>=1.6.0
Requires-Dist: requests>=2.32.0,<3
Requires-Dist: aiohttp>=3.9.2, <4
Requires-Dist: tenacity>=9.0
Requires-Dist: black ; extra == "dev"
Requires-Dist: build ; extra == "dev"
Requires-Dist: flake8 ; extra == "dev"
Requires-Dist: isort ; extra == "dev"
Requires-Dist: pre-commit ; extra == "dev"
Requires-Dist: twine ; extra == "dev"
Requires-Dist: apache-airflow-providers-standard ; extra == "standard"
Project-URL: Bug Tracker, https://github.com/apache/airflow/issues
Project-URL: Changelog, https://airflow.apache.org/docs/apache-airflow-providers-taskette/0.0.0/changelog.html
Project-URL: Documentation, https://airflow.apache.org/docs/apache-airflow-providers-taskette/0.0.0
Project-URL: Mastodon, https://fosstodon.org/@airflow
Project-URL: Slack Chat, https://s.apache.org/airflow-slack
Project-URL: Source Code, https://github.com/apache/airflow
Provides-Extra: dev
Provides-Extra: standard
